jaxlem/__init__.py
jaxlem/gradientdescent/__init__.py
jaxlem/gradientdescent/gradientdescent_utils.py
jaxlem/randomfield/__init__.py
jaxlem/randomfield/randomfield_utils.py
jaxlem/stability/__init__.py
jaxlem/stability/plotting_utils.py
jaxlem/stability/stability.py
jaxlem/stability/stability_utils.py
jaxlem-0.1.8.dist-info/LICENSE
jaxlem-0.1.8.dist-info/LICENSE.txt
jaxlem-0.1.8.dist-info/METADATA
jaxlem-0.1.8.dist-info/WHEEL
jaxlem-0.1.8.dist-info/RECORD
